setup.py
s3scrot/__init__.py
s3scrot/s3scrot.py
s3scrot.egg-info/PKG-INFO
s3scrot.egg-info/SOURCES.txt
s3scrot.egg-info/dependency_links.txt
s3scrot.egg-info/entry_points.txt
s3scrot.egg-info/not-zip-safe
s3scrot.egg-info/requires.txt
s3scrot.egg-info/top_level.txt