Metadata-Version: 1.0
Name: s3scrot
Version: 1.0
Summary: Tool to capture and upload screenshots to Amazon S3
Home-page: https://github.com/EnigmaCurry/s3scrot
Author: Ryan McGuire
Author-email: ryan@enigmacurry.com
License: UNKNOWN
Platform: UNKNOWN
